{
  "params": {
    "degree": 19,
    "num_rlc_columns": 1,
    "num_range_advice": [
      30,
      0,
      0
    ],
    "num_lookup_advice": [
      4,
      0,
      0
    ],
    "num_fixed": 1,
    "unusable_rows": 109,
    "keccak_rows_per_round": 50,
    "lookup_bits": 18
  },
  "break_points": {
    "gate": [
      [
        524178,
        524177,
        524178,
        524176,
        524177,
        524177,
        524176,
        524176,
        524177,
        524177,
        524176,
        524178,
        524178,
        524177,
        524178,
        524178,
        524178,
        524178,
        524176,
        524177,
        524178,
        524177,
        524177,
        524178,
        524177,
        524178,
        524176,
        524178,
        524178
      ],
      [],
      []
    ],
    "rlc": []
  }
}